README.rst
setup.py
src/unixaccount.py
src/unixaccount.egg-info/PKG-INFO
src/unixaccount.egg-info/SOURCES.txt
src/unixaccount.egg-info/dependency_links.txt
src/unixaccount.egg-info/top_level.txt
src/unixaccount.egg-info/zip-safe