Metadata-Version: 1.1
Name: unixaccount
Version: 0.1.1
Summary: Python module to manipulate unix system accounts.
Home-page: https://github.com/beli-sk/unixaccount
Author: Michal Belica
Author-email: devel@beli.sk
License: GPL
Platform: UNKNOWN
Classifier: Development Status :: 4 - Beta
Classifier: Environment :: Console
Classifier: License :: OSI Approved :: GNU General Public License v3 or later (GPLv3+)
Classifier: Programming Language :: Python :: 2.7
Classifier: Topic :: Utilities
